MANIFEST.in
README.txt
bootstrap.py
buildout.cfg
setup.cfg
setup.py
test-plone3.cfg
collective/__init__.py
collective.imagetags.egg-info/PKG-INFO
collective.imagetags.egg-info/SOURCES.txt
collective.imagetags.egg-info/dependency_links.txt
collective.imagetags.egg-info/entry_points.txt
collective.imagetags.egg-info/namespace_packages.txt
collective.imagetags.egg-info/not-zip-safe
collective.imagetags.egg-info/paster_plugins.txt
collective.imagetags.egg-info/requires.txt
collective.imagetags.egg-info/top_level.txt
collective/imagetags/__init__.py
collective/imagetags/configure.zcml
collective/imagetags/interfaces.py
collective/imagetags/profiles.zcml
collective/imagetags/rebuild_i18n.sh
collective/imagetags/setuphandlers.py
collective/imagetags/upgrades.py
collective/imagetags/vocabulary.py
collective/imagetags/adapters/__init__.py
collective/imagetags/adapters/configure.zcml
collective/imagetags/adapters/forms.py
collective/imagetags/adapters/interfaces.py
collective/imagetags/adapters/manager.py
collective/imagetags/browser/__init__.py
collective/imagetags/browser/configure.zcml
collective/imagetags/browser/controlpanel.py
collective/imagetags/browser/forms.py
collective/imagetags/browser/helper.py
collective/imagetags/browser/image.py
collective/imagetags/browser/interfaces.py
collective/imagetags/browser/js_labels.py
collective/imagetags/browser/manage.py
collective/imagetags/browser/new_tag_response.py
collective/imagetags/browser/viewlet.py
collective/imagetags/browser/resources/blank.gif
collective/imagetags/browser/resources/icon.png
collective/imagetags/browser/resources/image-tags.css
collective/imagetags/browser/resources/manage-tags.js
collective/imagetags/browser/resources/tag-center.gif
collective/imagetags/browser/resources/view-tags.js
collective/imagetags/browser/templates/controlpanel_layout.pt
collective/imagetags/browser/templates/form.pt
collective/imagetags/browser/templates/image.pt
collective/imagetags/browser/templates/manage.pt
collective/imagetags/browser/templates/new_tag_response.pt
collective/imagetags/browser/templates/tag_box.pt
collective/imagetags/browser/templates/tag_title.pt
collective/imagetags/browser/templates/viewlet.pt
collective/imagetags/docs/browser.txt
collective/imagetags/docs/vocabulary.txt
collective/imagetags/locales/collective.imagetags.pot
collective/imagetags/locales/en/LC_MESSAGES/collective.imagetags.mo
