Metadata-Version: 1.0
Name: collective.imagetags
Version: 1.5
Summary: Adds Facebook-like tags (or Flickr-like notes) to images
Home-page: http://svn.plone.org/svn/collective/collective.imagetags
Author: Marcos F. Romero
Author-email: marcos.romero {at} inter-cultura {dot} com
License: GPL
Platform: UNKNOWN
Classifier: Framework :: Plone
Classifier: Programming Language :: Python
